pyliveatc/models/audio_stream.py
pyliveatc/models/recording.py
pyliveatc/recording.py
pyliveatc/utils.py
pyliveatc-0.1.0.dist-info/LICENSE
pyliveatc-0.1.0.dist-info/WHEEL
pyliveatc-0.1.0.dist-info/METADATA
pyliveatc-0.1.0.dist-info/RECORD
